Metadata-Version: 2.1
Name: json-handler
Version: 2.0.1
Summary: Manipulate JSON data or dict values as attributes of an object.
Home-page: https://github.com/WexxanBest/json_handler
Author: WexxanBest
Author-email: WexxanBest@yandex.ru
License: MIT
Download-URL: http://pypi.python.org/pypi/json_handler/
Platform: UNKNOWN
Classifier: Topic :: Utilities
Classifier: Natural Language :: English
Classifier: Operating System :: OS Independent
Classifier: License :: OSI Approved :: MIT License
Classifier: Intended Audience :: Developers
Classifier: Development Status :: 4 - Beta
Classifier: Programming Language :: Python :: 3.8
License-File: LICENSE.txt
